CHANGES.rst
LICENSE.txt
MANIFEST.in
README.rst
buildout.cfg
setup.py
src/psycopg2transaction/__init__.py
src/psycopg2transaction/tests.py
src/psycopg2transaction.egg-info/PKG-INFO
src/psycopg2transaction.egg-info/SOURCES.txt
src/psycopg2transaction.egg-info/dependency_links.txt
src/psycopg2transaction.egg-info/entry_points.txt
src/psycopg2transaction.egg-info/not-zip-safe
src/psycopg2transaction.egg-info/requires.txt
src/psycopg2transaction.egg-info/top_level.txt