Metadata-Version: 1.1
Name: psycopg2transaction
Version: 0.1.1
Summary: psycopg2 integration with transaction
Home-page: https://github.com/jimfulton/psycopg2transaction
Author: Jim Fulton
Author-email: jim@jimfulton.info
License: MIT
Keywords: psycopg2,transaction,postgres,database
Platform: UNKNOWN
Classifier: Development Status :: 5 - Production/Stable
Classifier: Framework :: Buildout
Classifier: Intended Audience :: Developers
Classifier: License :: OSI Approved :: MIT License
Classifier: Programming Language :: Python
Classifier: Programming Language :: Python :: 2
Classifier: Programming Language :: Python :: 2.7
Classifier: Programming Language :: Python :: 3
Classifier: Programming Language :: Python :: 3.4
Classifier: Programming Language :: Python :: 3.5
Classifier: Programming Language :: Python :: 3.6
